dinky_weather/__init__.py
dinky_weather/assets.py
dinky_weather/fonts/Roboto-Bold.ttf
dinky_weather/fonts/Roboto-Regular.ttf
dinky_weather/fonts/__init__.py
dinky_weather-0.2.dist-info/LICENSE
dinky_weather-0.2.dist-info/METADATA
dinky_weather-0.2.dist-info/WHEEL
dinky_weather-0.2.dist-info/top_level.txt
dinky_weather-0.2.dist-info/RECORD
