Metadata-Version: 2.1
Name: dinky-weather
Version: 0.2
Summary: Weather widget for the dinky dashboard
Author: Julian Prester
License: MIT
Requires-Python: >=3.8
License-File: LICENSE
Requires-Dist: dinky
Requires-Dist: pluggy
Requires-Dist: Pillow
Requires-Dist: requests
Requires-Dist: setuptools
Provides-Extra: test
Requires-Dist: pytest ; extra == 'test'
